minecraft_model_reader/__init__.py
minecraft_model_reader/_version.py
minecraft_model_reader/py.typed
minecraft_model_reader/__pyinstaller/__init__.py
minecraft_model_reader/__pyinstaller/hook-minecraft_model_reader.py
minecraft_model_reader/api/__init__.py
minecraft_model_reader/api/comment_json.py
minecraft_model_reader/api/amulet/__init__.py
minecraft_model_reader/api/amulet/block.py
minecraft_model_reader/api/image/__init__.py
minecraft_model_reader/api/image/missing_no.png
minecraft_model_reader/api/image/missing_pack_java.png
minecraft_model_reader/api/mesh/__init__.py
minecraft_model_reader/api/mesh/util.py
minecraft_model_reader/api/mesh/block/__init__.py
minecraft_model_reader/api/mesh/block/block_mesh.py
minecraft_model_reader/api/mesh/block/cube.py
minecraft_model_reader/api/mesh/block/missing_block.py
minecraft_model_reader/api/resource_pack/__init__.py
minecraft_model_reader/api/resource_pack/unknown_resource_pack.py
minecraft_model_reader/api/resource_pack/base/__init__.py
minecraft_model_reader/api/resource_pack/base/resource_pack.py
minecraft_model_reader/api/resource_pack/base/resource_pack_manager.py
minecraft_model_reader/api/resource_pack/bedrock/__init__.py
minecraft_model_reader/api/resource_pack/bedrock/block_palette.json
minecraft_model_reader/api/resource_pack/bedrock/blockshapes.json
minecraft_model_reader/api/resource_pack/bedrock/download_resources.py
minecraft_model_reader/api/resource_pack/bedrock/resource_pack.py
minecraft_model_reader/api/resource_pack/bedrock/resource_pack_manager.py
minecraft_model_reader/api/resource_pack/bedrock/sort_blockshapes.py
minecraft_model_reader/api/resource_pack/bedrock/bedrock_vanilla_fix/blocks.json
minecraft_model_reader/api/resource_pack/bedrock/bedrock_vanilla_fix/manifest.json
minecraft_model_reader/api/resource_pack/bedrock/bedrock_vanilla_fix/pack_icon.png
minecraft_model_reader/api/resource_pack/bedrock/bedrock_vanilla_fix/textures/terrain_texture.json
minecraft_resource_pack-1.4.6.dist-info/LICENSE
minecraft_resource_pack-1.4.6.dist-info/METADATA
minecraft_resource_pack-1.4.6.dist-info/WHEEL
minecraft_resource_pack-1.4.6.dist-info/entry_points.txt
minecraft_resource_pack-1.4.6.dist-info/top_level.txt
minecraft_resource_pack-1.4.6.dist-info/RECORD
